tktimepicker/__init__.py
tktimepicker/basetimepicker.py
tktimepicker/constants.py
tktimepicker/spinlabel.py
tktimepicker/timepicker.py
tkTimePicker-2.0.1.dist-info/LICENSE.txt
tkTimePicker-2.0.1.dist-info/METADATA
tkTimePicker-2.0.1.dist-info/WHEEL
tkTimePicker-2.0.1.dist-info/top_level.txt
tkTimePicker-2.0.1.dist-info/RECORD
