Metadata-Version: 2.1
Name: tkTimePicker
Version: 2.0.1
Summary: This package provides you with easy to customize timepickers
Home-page: https://github.com/PaulleDemon/tkTimePicker
Author: Paul
License: MIT
Keywords: tkinter,timepicker,time,tktimepicker
Platform: UNKNOWN
Classifier: License :: OSI Approved :: MIT License
Classifier: Programming Language :: Python :: 3.6
Classifier: Programming Language :: Python :: 3.7
Classifier: Programming Language :: Python :: 3.8
Classifier: Programming Language :: Python :: 3.9
Classifier: Programming Language :: Python :: 3.10
Requires-Python: >=3.6
